base_plans/__init__.py
base_plans/apps.py
base_plans/models.py
django_rd2_plans-0.0.1.dist-info/LICENSE
django_rd2_plans-0.0.1.dist-info/METADATA
django_rd2_plans-0.0.1.dist-info/WHEEL
django_rd2_plans-0.0.1.dist-info/top_level.txt
django_rd2_plans-0.0.1.dist-info/RECORD
