Metadata-Version: 2.1
Name: django-rd2-plans
Version: 0.0.1
Summary: Base de modelos de planos usados na RD2
Home-page: https://github.com/alessandrak/django-rd2-plans
Author: Alessandra Carneiro
Author-email: alessandra@rd2.ventures
License: UNKNOWN
Platform: UNKNOWN
Classifier: Programming Language :: Python :: 3
Classifier: Framework :: Django :: 3.1
Classifier: License :: OSI Approved :: MIT License
Classifier: Operating System :: OS Independent
Requires-Python: >=3.7
